Metadata-Version: 2.1
Name: animaljam
Version: 0.0.3
Summary: Create Animal Jam bots with ease!
Home-page: UNKNOWN
Author: Afraid
Author-email: afraidowns@protonmail.com
License: MIT
Keywords: animaljam
Platform: UNKNOWN
Classifier: Development Status :: 5 - Production/Stable
Classifier: Intended Audience :: Education
Classifier: Operating System :: Microsoft :: Windows :: Windows 10
Classifier: License :: OSI Approved :: MIT License
Classifier: Programming Language :: Python :: 3
License-File: LICENCE.txt
